pxk/Constants.py
pxk/__init__.py
pxk/conftest.py
pxk/k8_client.py
pxk/ms_socketserver.py
pxk/plugin.py
pxk-0.0.4.dist-info/LICENSE
pxk-0.0.4.dist-info/METADATA
pxk-0.0.4.dist-info/WHEEL
pxk-0.0.4.dist-info/entry_points.txt
pxk-0.0.4.dist-info/RECORD
