Metadata-Version: 2.1
Name: pxk
Version: 0.0.4
Summary: Automate the process of distributed testing on a Kubernetes cluster by extending the functionality of pytest-xdist, allowing users to efficiently run tests in parallel across multiple pods.
License: MIT
Author: Aiden Seo
Author-email: minwoo3180@gmail.com
Requires-Python: >=3.9,<4.0
Classifier: Framework :: Pytest
Classifier: License :: OSI Approved :: MIT License
Classifier: Programming Language :: Python :: 3
Classifier: Programming Language :: Python :: 3.9
Classifier: Programming Language :: Python :: 3.10
Classifier: Programming Language :: Python :: 3.11
Classifier: Programming Language :: Python :: 3.12
Requires-Dist: execnet (>=2.1.1,<3.0.0)
Requires-Dist: kubernetes (>=29.0.0,<30.0.0)
Requires-Dist: pytest (>=7.4.4,<8.0.0)
Requires-Dist: pytest-xdist (>=3.5.0,<4.0.0)
Requires-Dist: tenacity (>=8.2.3,<9.0.0)
